renderspec/__init__.py
renderspec/contextfuncs.py
renderspec/distloader.py
renderspec/utils.py
renderspec/versions.py
renderspec/dist-templates/fedora.spec.j2
renderspec/dist-templates/suse.spec.j2
renderspec-2.3.0.dist-info/AUTHORS
renderspec-2.3.0.dist-info/LICENSE
renderspec-2.3.0.dist-info/METADATA
renderspec-2.3.0.dist-info/WHEEL
renderspec-2.3.0.dist-info/entry_points.txt
renderspec-2.3.0.dist-info/pbr.json
renderspec-2.3.0.dist-info/top_level.txt
renderspec-2.3.0.dist-info/RECORD
