Metadata-Version: 2.1
Name: renderspec
Version: 2.3.0
Summary: Jinja2 template renderer for generating .spec files
Home-page: https://docs.openstack.org/renderspec/latest/
Author: OpenStack
Author-email: openstack-discuss@lists.openstack.org
License: UNKNOWN
Platform: UNKNOWN
Classifier: Environment :: Console
Classifier: Environment :: OpenStack
Classifier: Intended Audience :: Information Technology
Classifier: Intended Audience :: System Administrators
Classifier: License :: OSI Approved :: Apache Software License
Classifier: Operating System :: POSIX :: Linux
Classifier: Programming Language :: Python
Classifier: Programming Language :: Python :: Implementation :: CPython
Classifier: Programming Language :: Python :: 3 :: Only
Classifier: Programming Language :: Python :: 3
Classifier: Programming Language :: Python :: 3.8
Classifier: Programming Language :: Python :: 3.9
Requires-Python: >=3.8
Requires-Dist: Jinja2 (>=2.10)
Requires-Dist: PyYAML (>=3.10)
Requires-Dist: packaging (>=16.5)
Requires-Dist: pymod2pkg (!=0.8.0,>=0.7.0)
